pod5_format/__init__.py
pod5_format/_version.py
pod5_format/api_utils.py
pod5_format/pod5_format_pybind.cpython-39-darwin.so
pod5_format/pod5_format_pybind.pyi
pod5_format/pod5_types.py
pod5_format/reader.py
pod5_format/repack.py
pod5_format/signal_tools.py
pod5_format/writer.py
pod5_format-0.0.41.dist-info/METADATA
pod5_format-0.0.41.dist-info/WHEEL
pod5_format-0.0.41.dist-info/top_level.txt
pod5_format-0.0.41.dist-info/RECORD
