Metadata-Version: 2.1
Name: pod5-format
Version: 0.0.41
Summary: Python bindings for the POD5 file format
Home-page: https://github.com/nanoporetech/pod5-file-format
Author: Oxford Nanopore Technologies plc
Author-email: support@nanoporetech.com
License: UNKNOWN
Platform: UNKNOWN
Requires-Dist: iso8601
Requires-Dist: more-itertools
Requires-Dist: numpy (>=1.20.0)
Requires-Dist: packaging
Requires-Dist: pyarrow (~=8.0.0)
Requires-Dist: pytz
